mechlib/__init__.py
mechlib/image.py
mechlib/mech.py
mechlib/mechbattle.py
mechlib/motor.py
mechlib/network.py
mechlib/README.md
mechlib/strategy.py
mechlib/time_wraper.py
mechlib/utils.py
mechlib-0.1.0.dist-info/entry_points.txt
mechlib-0.1.0.dist-info/LICENSE
mechlib-0.1.0.dist-info/METADATA
mechlib-0.1.0.dist-info/WHEEL
mechlib-0.1.0.dist-info/RECORD
