Metadata-Version: 2.1
Name: mechlib
Version: 0.1.0
Summary: Mech Library for MechBattles
License: MIT
Author: Ric Pruss
Author-email: ricpruss@gmail.com
Requires-Python: >=3.10,<=3.11
Classifier: License :: OSI Approved :: MIT License
Classifier: Programming Language :: Python :: 3
Classifier: Programming Language :: Python :: 3.10
Classifier: Programming Language :: Python :: 3.11
Requires-Dist: protobuf (<4.0.0)
Requires-Dist: roboflow (>=0.2.29,<0.3.0)
Requires-Dist: torch (>=1.13.1,<2.0.0)
Requires-Dist: torchvision (>=0.14.1,<0.15.0)
Requires-Dist: ultralytics (>=8.0.20,<9.0.0)
